{
  "versions": [
    {
      "git-tree": "801e9d2fecd40f26b85b845c940a342510b83713",
      "version-semver": "1.16.2",
      "port-version": 1
    },
    {
      "git-tree": "39cd4efb2f7e3c014a8a8657aa266bf9d10f7a89",
      "version-semver": "1.16.2",
      "port-version": 0
    },
    {
      "git-tree": "d248e60e662d69653111b414ce11362620272fba",
      "version-semver": "1.16.1",
      "port-version": 0
    },
    {
      "git-tree": "7da4ed72675423754cd88d6ef4f7f1c0acc4903e",
      "version-semver": "1.16.0",
      "port-version": 2
    },
    {
      "git-tree": "84056c069b4cc59b487fc92bbcebb5aaa22b7f9b",
      "version-semver": "1.16.0",
      "port-version": 1
    },
    {
      "git-tree": "1af25fe8c665cace7ea7cf3e1076d8a77ac2ce70",
      "version-semver": "1.16.0",
      "port-version": 0
    },
    {
      "git-tree": "efbeae02e9bd54250b93e1f91e3b570b347fe69d",
      "version-semver": "1.15.0",
      "port-version": 2
    },
    {
      "git-tree": "fd1d8cd2b64f75ba7c9d34f1d4364ba3d038ac73",
      "version-semver": "1.15.0",
      "port-version": 1
    },
    {
      "git-tree": "18fa90d742ae729066d99e418a07a4a8f00e34be",
      "version-semver": "1.15.0",
      "port-version": 0
    },
    {
      "git-tree": "cd5846d14598c277b59388adfb2977a99cbea292",
      "version-semver": "1.14.1",
      "port-version": 2
    },
    {
      "git-tree": "7011da9a989a72143c55f0894c8014be136caada",
      "version-semver": "1.14.1",
      "port-version": 1
    },
    {
      "git-tree": "7b3356ece5980df538926a7429f2fdff883f4cae",
      "version-semver": "1.14.1",
      "port-version": 0
    },
    {
      "git-tree": "4df044138d042ad4f2ae202b657f7e32ab820414",
      "version-semver": "1.12.0",
      "port-version": 0
    },
    {
      "git-tree": "5b14f10634fdcd02f8eed5d05274aa447012a08e",
      "version-semver": "1.10.2",
      "port-version": 0
    }
  ]
}
